toktab/__init__.py
toktab/api.py
toktab/cli.py
toktab/display.py
toktab-0.1.0.dist-info/METADATA
toktab-0.1.0.dist-info/WHEEL
toktab-0.1.0.dist-info/entry_points.txt
toktab-0.1.0.dist-info/licenses/LICENSE
toktab-0.1.0.dist-info/RECORD
