Metadata-Version: 2.4
Name: toktab
Version: 0.1.0
Summary: CLI tool for TokTab LLM pricing data
Project-URL: Homepage, https://github.com/tomdyson/toktab-cli
Project-URL: Repository, https://github.com/tomdyson/toktab-cli
Project-URL: Issues, https://github.com/tomdyson/toktab-cli/issues
Author-email: Tom Dyson <tom@torchbox.com>
License-Expression: MIT
License-File: LICENSE
Keywords: ai,cli,llm,pricing,toktab
Classifier: Development Status :: 4 - Beta
Classifier: Environment :: Console
Classifier: Intended Audience :: Developers
Classifier: License :: OSI Approved :: MIT License
Classifier: Operating System :: OS Independent
Classifier: Programming Language :: Python :: 3
Classifier: Programming Language :: Python :: 3.10
Classifier: Programming Language :: Python :: 3.11
Classifier: Programming Language :: Python :: 3.12
Classifier: Programming Language :: Python :: 3.13
Classifier: Topic :: Software Development :: Libraries :: Python Modules
Requires-Python: >=3.10
Requires-Dist: click>=8.0
Requires-Dist: httpx>=0.24
Requires-Dist: rich>=13.0
Provides-Extra: dev
Requires-Dist: pytest-httpx>=0.21; extra == 'dev'
Requires-Dist: pytest>=7.0; extra == 'dev'
